src/fifo_8x64.v
module fifo_8x64 (
    input clk,                  // Clock input
    input rst,                  // Reset input
    input wr_en,                // Write enable
    input rd_en,                // Read enable
    input [7:0] data_in,        // Data input
    output reg [7:0] data_out,  // Data output
    output reg full,            // FIFO full flag
    output reg empty            // FIFO empty flag
);

// FIFO memory array
reg [7:0] fifo_mem[63:0];

// Read and write pointers
reg [5:0] write_pointer, read_pointer;

// Counter to keep track of the number of items in the FIFO
reg [6:0] count;

// Write operation
always @(posedge clk) begin
    if (rst) begin
        write_pointer <= 0;
        full <= 0;
    end else if (wr_en && !full) begin
        fifo_mem[write_pointer] <= data_in;
        write_pointer <= write_pointer + 1;
        if (write_pointer == 63) full <= 1;
    end
    if (wr_en && !full) begin
        count <= count + 1;
        empty <= 0;
    end
end

// Read operation
always @(posedge clk) begin
    if (rst) begin
        read_pointer <= 0;
        empty <= 1;
    end else if (rd_en && !empty) begin
        data_out <= fifo_mem[read_pointer];
        read_pointer <= read_pointer + 1;
        if (read_pointer == 63) empty <= 1;
    end
    if (rd_en && !empty) begin
        count <= count - 1;
        full <= 0;
    end
end

// FIFO full and empty logic
always @(*) begin
    full = (count == 64);
    empty = (count == 0);
end

endmodule

test/fifo/fifo_tb.sv
`timescale 1ns / 1ps

module fifo_8x64_tb;

reg clk;
reg rst;
reg wr_en;
reg rd_en;
reg [7:0] data_in;
wire [7:0] data_out;
wire full;
wire empty;

// Instantiate the FIFO module
fifo_8x64 uut (
    .clk(clk),
    .rst(rst),
    .wr_en(wr_en),
    .rd_en(rd_en),
    .data_in(data_in),
    .data_out(data_out),
    .full(full),
    .empty(empty)
);

// Clock generation
always #5 clk = ~clk; // Generate a clock with a period of 10 ns

integer file;
initial begin
    file = $fopen("test/fifo/output_data.txt", "w");
    if (file == 0) begin
        $display("Failed to open file.");
        $finish;
    end
end


// Test sequence
initial begin
    // Initialize inputs
    clk = 0;
    rst = 1;
    wr_en = 0;
    rd_en = 0;
    data_in = 0;
    
    // Reset the FIFO
    #10;
    rst = 0;
    
    // Write data into the FIFO
    repeat (65) begin
        #10;
        if (!full) begin
            wr_en = 1;
            data_in = data_in + 1; // Increment data for each write
        end else wr_en = 0; // If FIFO is full, stop writing
    end
    wr_en = 0; // Ensure write enable is disabled
    
    // Read data from the FIFO
    repeat (65) begin
        #10;
        if (!empty) rd_en = 1; // If FIFO is not empty, enable read
        else rd_en = 0; // If FIFO is empty, stop reading
    end
    rd_en = 0; // Ensure read enable is disabled
    
    // Complete simulation
    #100;
    $finish;
end

// In the part of your testbench where you want to record data_out
always @(posedge clk) begin
    if (rd_en) begin
        $fwrite(file, "%d\n", data_out); // Writing data_out to file
    end
end


initial begin
    // Initialize VCD dump
    $dumpfile("test/fifo/fifo_tb.vcd");
    $dumpvars(0, fifo_8x64_tb);
end

initial begin
    #10000; // Adjust the time according to your simulation
    $fclose(file);
    $finish;
end

endmodule

test/fifo/fifo_tb.vcd
$date
	Mon Feb 12 11:44:35 2024
$end
$version
	Icarus Verilog
$end
$timescale
	1ps
$end
$scope module fifo_8x64_tb $end
$var wire 1 ! full $end
$var wire 1 " empty $end
$var wire 8 # data_out [7:0] $end
$var reg 1 $ clk $end
$var reg 8 % data_in [7:0] $end
$var reg 1 & rd_en $end
$var reg 1 ' rst $end
$var reg 1 ( wr_en $end
$var integer 32 ) file [31:0] $end
$scope module uut $end
$var wire 1 $ clk $end
$var wire 8 * data_in [7:0] $end
$var wire 1 & rd_en $end
$var wire 1 ' rst $end
$var wire 1 ( wr_en $end
$var reg 7 + count [6:0] $end
$var reg 8 , data_out [7:0] $end
$var reg 1 " empty $end
$var reg 1 ! full $end
$var reg 6 - read_pointer [5:0] $end
$var reg 6 . write_pointer [5:0] $end
$upscope $end
$upscope $end
$enddefinitions $end
$comment Show the parameter values. $end
$dumpall
$end
#0
$dumpvars
bx .
bx -
bx ,
bx +
b0 *
b10000000000000000000000000000011 )
0(
1'
0&
b0 %
0$
bx #
x"
x!
$end
#5000
0!
b0 .
1"
b0 -
1$
#10000
0$
0'
#15000
1$
#20000
0$
b1 %
b1 *
1(
#25000
0"
b1 .
1$
#30000
0$
b10 %
b10 *
#35000
b10 .
1$
#40000
0$
b11 %
b11 *
#45000
b11 .
1$
#50000
0$
b100 %
b100 *
#55000
b100 .
1$
#60000
0$
b101 %
b101 *
#65000
b101 .
1$
#70000
0$
b110 %
b110 *
#75000
b110 .
1$
#80000
0$
b111 %
b111 *
#85000
b111 .
1$
#90000
0$
b1000 %
b1000 *
#95000
b1000 .
1$
#100000
0$
b1001 %
b1001 *
#105000
b1001 .
1$
#110000
0$
b1010 %
b1010 *
#115000
b1010 .
1$
#120000
0$
b1011 %
b1011 *
#125000
b1011 .
1$
#130000
0$
b1100 %
b1100 *
#135000
b1100 .
1$
#140000
0$
b1101 %
b1101 *
#145000
b1101 .
1$
#150000
0$
b1110 %
b1110 *
#155000
b1110 .
1$
#160000
0$
b1111 %
b1111 *
#165000
b1111 .
1$
#170000
0$
b10000 %
b10000 *
#175000
b10000 .
1$
#180000
0$
b10001 %
b10001 *
#185000
b10001 .
1$
#190000
0$
b10010 %
b10010 *
#195000
b10010 .
1$
#200000
0$
b10011 %
b10011 *
#205000
b10011 .
1$
#210000
0$
b10100 %
b10100 *
#215000
b10100 .
1$
#220000
0$
b10101 %
b10101 *
#225000
b10101 .
1$
#230000
0$
b10110 %
b10110 *
#235000
b10110 .
1$
#240000
0$
b10111 %
b10111 *
#245000
b10111 .
1$
#250000
0$
b11000 %
b11000 *
#255000
b11000 .
1$
#260000
0$
b11001 %
b11001 *
#265000
b11001 .
1$
#270000
0$
b11010 %
b11010 *
#275000
b11010 .
1$
#280000
0$
b11011 %
b11011 *
#285000
b11011 .
1$
#290000
0$
b11100 %
b11100 *
#295000
b11100 .
1$
#300000
0$
b11101 %
b11101 *
#305000
b11101 .
1$
#310000
0$
b11110 %
b11110 *
#315000
b11110 .
1$
#320000
0$
b11111 %
b11111 *
#325000
b11111 .
1$
#330000
0$
b100000 %
b100000 *
#335000
b100000 .
1$
#340000
0$
b100001 %
b100001 *
#345000
b100001 .
1$
#350000
0$
b100010 %
b100010 *
#355000
b100010 .
1$
#360000
0$
b100011 %
b100011 *
#365000
b100011 .
1$
#370000
0$
b100100 %
b100100 *
#375000
b100100 .
1$
#380000
0$
b100101 %
b100101 *
#385000
b100101 .
1$
#390000
0$
b100110 %
b100110 *
#395000
b100110 .
1$
#400000
0$
b100111 %
b100111 *
#405000
b100111 .
1$
#410000
0$
b101000 %
b101000 *
#415000
b101000 .
1$
#420000
0$
b101001 %
b101001 *
#425000
b101001 .
1$
#430000
0$
b101010 %
b101010 *
#435000
b101010 .
1$
#440000
0$
b101011 %
b101011 *
#445000
b101011 .
1$
#450000
0$
b101100 %
b101100 *
#455000
b101100 .
1$
#460000
0$
b101101 %
b101101 *
#465000
b101101 .
1$
#470000
0$
b101110 %
b101110 *
#475000
b101110 .
1$
#480000
0$
b101111 %
b101111 *
#485000
b101111 .
1$
#490000
0$
b110000 %
b110000 *
#495000
b110000 .
1$
#500000
0$
b110001 %
b110001 *
#505000
b110001 .
1$
#510000
0$
b110010 %
b110010 *
#515000
b110010 .
1$
#520000
0$
b110011 %
b110011 *
#525000
b110011 .
1$
#530000
0$
b110100 %
b110100 *
#535000
b110100 .
1$
#540000
0$
b110101 %
b110101 *
#545000
b110101 .
1$
#550000
0$
b110110 %
b110110 *
#555000
b110110 .
1$
#560000
0$
b110111 %
b110111 *
#565000
b110111 .
1$
#570000
0$
b111000 %
b111000 *
#575000
b111000 .
1$
#580000
0$
b111001 %
b111001 *
#585000
b111001 .
1$
#590000
0$
b111010 %
b111010 *
#595000
b111010 .
1$
#600000
0$
b111011 %
b111011 *
#605000
b111011 .
1$
#610000
0$
b111100 %
b111100 *
#615000
b111100 .
1$
#620000
0$
b111101 %
b111101 *
#625000
b111101 .
1$
#630000
0$
b111110 %
b111110 *
#635000
b111110 .
1$
#640000
0$
b111111 %
b111111 *
#645000
b111111 .
1$
#650000
0$
b1000000 %
b1000000 *
#655000
1!
b0 .
1$
#660000
0$
0(
#665000
1$
#670000
0$
1&
#675000
0!
b1 -
b1 #
b1 ,
1$
#680000
0$
#685000
b10 -
b10 #
b10 ,
1$
#690000
0$
#695000
b11 -
b11 #
b11 ,
1$
#700000
0$
#705000
b100 -
b100 #
b100 ,
1$
#710000
0$
#715000
b101 -
b101 #
b101 ,
1$
#720000
0$
#725000
b110 -
b110 #
b110 ,
1$
#730000
0$
#735000
b111 -
b111 #
b111 ,
1$
#740000
0$
#745000
b1000 -
b1000 #
b1000 ,
1$
#750000
0$
#755000
b1001 -
b1001 #
b1001 ,
1$
#760000
0$
#765000
b1010 -
b1010 #
b1010 ,
1$
#770000
0$
#775000
b1011 -
b1011 #
b1011 ,
1$
#780000
0$
#785000
b1100 -
b1100 #
b1100 ,
1$
#790000
0$
#795000
b1101 -
b1101 #
b1101 ,
1$
#800000
0$
#805000
b1110 -
b1110 #
b1110 ,
1$
#810000
0$
#815000
b1111 -
b1111 #
b1111 ,
1$
#820000
0$
#825000
b10000 -
b10000 #
b10000 ,
1$
#830000
0$
#835000
b10001 -
b10001 #
b10001 ,
1$
#840000
0$
#845000
b10010 -
b10010 #
b10010 ,
1$
#850000
0$
#855000
b10011 -
b10011 #
b10011 ,
1$
#860000
0$
#865000
b10100 -
b10100 #
b10100 ,
1$
#870000
0$
#875000
b10101 -
b10101 #
b10101 ,
1$
#880000
0$
#885000
b10110 -
b10110 #
b10110 ,
1$
#890000
0$
#895000
b10111 -
b10111 #
b10111 ,
1$
#900000
0$
#905000
b11000 -
b11000 #
b11000 ,
1$
#910000
0$
#915000
b11001 -
b11001 #
b11001 ,
1$
#920000
0$
#925000
b11010 -
b11010 #
b11010 ,
1$
#930000
0$
#935000
b11011 -
b11011 #
b11011 ,
1$
#940000
0$
#945000
b11100 -
b11100 #
b11100 ,
1$
#950000
0$
#955000
b11101 -
b11101 #
b11101 ,
1$
#960000
0$
#965000
b11110 -
b11110 #
b11110 ,
1$
#970000
0$
#975000
b11111 -
b11111 #
b11111 ,
1$
#980000
0$
#985000
b100000 -
b100000 #
b100000 ,
1$
#990000
0$
#995000
b100001 -
b100001 #
b100001 ,
1$
#1000000
0$
#1005000
b100010 -
b100010 #
b100010 ,
1$
#1010000
0$
#1015000
b100011 -
b100011 #
b100011 ,
1$
#1020000
0$
#1025000
b100100 -
b100100 #
b100100 ,
1$
#1030000
0$
#1035000
b100101 -
b100101 #
b100101 ,
1$
#1040000
0$
#1045000
b100110 -
b100110 #
b100110 ,
1$
#1050000
0$
#1055000
b100111 -
b100111 #
b100111 ,
1$
#1060000
0$
#1065000
b101000 -
b101000 #
b101000 ,
1$
#1070000
0$
#1075000
b101001 -
b101001 #
b101001 ,
1$
#1080000
0$
#1085000
b101010 -
b101010 #
b101010 ,
1$
#1090000
0$
#1095000
b101011 -
b101011 #
b101011 ,
1$
#1100000
0$
#1105000
b101100 -
b101100 #
b101100 ,
1$
#1110000
0$
#1115000
b101101 -
b101101 #
b101101 ,
1$
#1120000
0$
#1125000
b101110 -
b101110 #
b101110 ,
1$
#1130000
0$
#1135000
b101111 -
b101111 #
b101111 ,
1$
#1140000
0$
#1145000
b110000 -
b110000 #
b110000 ,
1$
#1150000
0$
#1155000
b110001 -
b110001 #
b110001 ,
1$
#1160000
0$
#1165000
b110010 -
b110010 #
b110010 ,
1$
#1170000
0$
#1175000
b110011 -
b110011 #
b110011 ,
1$
#1180000
0$
#1185000
b110100 -
b110100 #
b110100 ,
1$
#1190000
0$
#1195000
b110101 -
b110101 #
b110101 ,
1$
#1200000
0$
#1205000
b110110 -
b110110 #
b110110 ,
1$
#1210000
0$
#1215000
b110111 -
b110111 #
b110111 ,
1$
#1220000
0$
#1225000
b111000 -
b111000 #
b111000 ,
1$
#1230000
0$
#1235000
b111001 -
b111001 #
b111001 ,
1$
#1240000
0$
#1245000
b111010 -
b111010 #
b111010 ,
1$
#1250000
0$
#1255000
b111011 -
b111011 #
b111011 ,
1$
#1260000
0$
#1265000
b111100 -
b111100 #
b111100 ,
1$
#1270000
0$
#1275000
b111101 -
b111101 #
b111101 ,
1$
#1280000
0$
#1285000
b111110 -
b111110 #
b111110 ,
1$
#1290000
0$
#1295000
b111111 -
b111111 #
b111111 ,
1$
#1300000
0$
#1305000
1"
b0 -
b1000000 #
b1000000 ,
1$
#1310000
0$
0&
